agentnxt/__init__.py
agentnxt/agent.py
agentnxt/config.py
agentnxt/memory.py
agentnxt/orchestra.py
agentnxt/tools.py
agentnxt/workflow.py
agentnxt-0.1.0.dist-info/METADATA
agentnxt-0.1.0.dist-info/WHEEL
agentnxt-0.1.0.dist-info/top_level.txt
agentnxt-0.1.0.dist-info/RECORD
